setup.py
pyvod.egg-info/PKG-INFO
pyvod.egg-info/SOURCES.txt
pyvod.egg-info/dependency_links.txt
pyvod.egg-info/not-zip-safe
pyvod.egg-info/requires.txt
pyvod.egg-info/top_level.txt
vod/__init__.py
vod/video.py
vod/vodservice.py