Metadata-Version: 1.1
Name: pyvod
Version: 1.0
Summary: Pluzz TV Show Downloader
Home-page: http://m0g.net
Author: Bernard `Guyzmo` Pratz
Author-email: pyvodservice@m0g.net
License: GPLv3
Keywords: download tv show
Platform: UNKNOWN
Classifier: Development Status :: 4 - Beta
Classifier: License :: OSI Approved
Classifier: Operating System :: Unix
